mrequests/MultiRequests.py
mrequests/__init__.py
mrequests/mrequests.py
mrequests-0.1.2.dist-info/LICENSE
mrequests-0.1.2.dist-info/METADATA
mrequests-0.1.2.dist-info/WHEEL
mrequests-0.1.2.dist-info/top_level.txt
mrequests-0.1.2.dist-info/RECORD
