Metadata-Version: 2.1
Name: mrequests
Version: 0.1.2
Summary: UNKNOWN
Home-page: https://github.com/dannybritto96/mrequests
Author: Danie Britto
Author-email: dannybritto96@gmail.com
License: UNKNOWN
Platform: UNKNOWN
Classifier: Programming Language :: Python :: 3
Classifier: License :: OSI Approved :: MIT License
Classifier: Operating System :: OS Independent
Requires-Dist: requests
